README.md
setup.py
pulumi_datarobot/__init__.py
pulumi_datarobot/_inputs.py
pulumi_datarobot/_utilities.py
pulumi_datarobot/api_token_credential.py
pulumi_datarobot/app_oauth.py
pulumi_datarobot/application_source.py
pulumi_datarobot/application_source_from_template.py
pulumi_datarobot/aws_credential.py
pulumi_datarobot/azure_credential.py
pulumi_datarobot/basic_credential.py
pulumi_datarobot/batch_prediction_job_definition.py
pulumi_datarobot/custom_application.py
pulumi_datarobot/custom_application_from_environment.py
pulumi_datarobot/custom_job.py
pulumi_datarobot/custom_metric.py
pulumi_datarobot/custom_metric_from_job.py
pulumi_datarobot/custom_metric_job.py
pulumi_datarobot/custom_model.py
pulumi_datarobot/custom_model_llm_validation.py
pulumi_datarobot/dataset_from_datasource.py
pulumi_datarobot/dataset_from_file.py
pulumi_datarobot/dataset_from_url.py
pulumi_datarobot/datasource.py
pulumi_datarobot/datastore.py
pulumi_datarobot/deployment.py
pulumi_datarobot/deployment_retraining_policy.py
pulumi_datarobot/execution_environment.py
pulumi_datarobot/get_execution_environment.py
pulumi_datarobot/get_global_model.py
pulumi_datarobot/google_cloud_credential.py
pulumi_datarobot/llm_blueprint.py
pulumi_datarobot/notebook.py
pulumi_datarobot/notification_channel.py
pulumi_datarobot/notification_policy.py
pulumi_datarobot/outputs.py
pulumi_datarobot/playground.py
pulumi_datarobot/prediction_environment.py
pulumi_datarobot/provider.py
pulumi_datarobot/pulumi-plugin.json
pulumi_datarobot/py.typed
pulumi_datarobot/qa_application.py
pulumi_datarobot/registered_model.py
pulumi_datarobot/registered_model_from_leaderboard.py
pulumi_datarobot/remote_repository.py
pulumi_datarobot/use_case.py
pulumi_datarobot/vector_database.py
pulumi_datarobot.egg-info/PKG-INFO
pulumi_datarobot.egg-info/SOURCES.txt
pulumi_datarobot.egg-info/dependency_links.txt
pulumi_datarobot.egg-info/not-zip-safe
pulumi_datarobot.egg-info/requires.txt
pulumi_datarobot.egg-info/top_level.txt
pulumi_datarobot/config/__init__.py
pulumi_datarobot/config/__init__.pyi
pulumi_datarobot/config/vars.py