Metadata-Version: 2.4
Name: pulumi_datarobot
Version: 0.10.23
Summary: A Pulumi package for creating and managing DataRobot resources.
Home-page: https://www.datarobot.com
License: Apache-2.0
Project-URL: Repository, https://github.com/datarobot-community/pulumi-datarobot
Keywords: datarobot ai category/cloud
Requires-Python: >=3.9
Requires-Dist: parver>=0.2.1
Requires-Dist: pulumi<4.0.0,>=3.0.0
Requires-Dist: semver>=2.8.1
Requires-Dist: typing-extensions<5,>=4.11; python_version < "3.11"
Dynamic: description
Dynamic: description-content-type
Dynamic: home-page
Dynamic: keywords
Dynamic: license
Dynamic: project-url
Dynamic: requires-dist
Dynamic: requires-python
Dynamic: summary
